pyst_typesense_async-1.0.0.dist-info/licenses/LICENSE
typesense/__init__.py
typesense/alias.py
typesense/aliases.py
typesense/analytics.py
typesense/analytics_rule.py
typesense/analytics_rules.py
typesense/api_call.py
typesense/client.py
typesense/collection.py
typesense/collections.py
typesense/configuration.py
typesense/conversation_model.py
typesense/conversations_models.py
typesense/debug.py
typesense/document.py
typesense/documents.py
typesense/exceptions.py
typesense/key.py
typesense/keys.py
typesense/logger.py
typesense/multi_search.py
typesense/node_manager.py
typesense/operations.py
typesense/override.py
typesense/overrides.py
typesense/preprocess.py
typesense/py.typed
typesense/request_handler.py
typesense/stemming.py
typesense/stemming_dictionaries.py
typesense/stemming_dictionary.py
typesense/stopwords.py
typesense/stopwords_set.py
typesense/synonym.py
typesense/synonyms.py
typesense/types/__init__.py
typesense/types/alias.py
typesense/types/analytics_rule.py
typesense/types/collection.py
typesense/types/conversations_model.py
typesense/types/debug.py
typesense/types/document.py
typesense/types/key.py
typesense/types/multi_search.py
typesense/types/operations.py
typesense/types/override.py
typesense/types/stemming.py
typesense/types/stopword.py
typesense/types/synonym.py
pyst_typesense_async-1.0.0.dist-info/METADATA
pyst_typesense_async-1.0.0.dist-info/WHEEL
pyst_typesense_async-1.0.0.dist-info/top_level.txt
pyst_typesense_async-1.0.0.dist-info/RECORD
